octoprint_cli/__init__.py
octoprint_cli/__main__.py
octoprint_cli/api.py
octoprint_cli-3.3.2.post1.dist-info/licenses/LICENSE
octoprint_cli-3.3.2.post1.dist-info/METADATA
octoprint_cli-3.3.2.post1.dist-info/WHEEL
octoprint_cli-3.3.2.post1.dist-info/entry_points.txt
octoprint_cli-3.3.2.post1.dist-info/top_level.txt
octoprint_cli-3.3.2.post1.dist-info/RECORD
