Metadata-Version: 2.4
Name: octoprint-cli
Version: 3.3.2.post1
Summary: Command line tool for controlling your OctoPrint 3D printer server
Home-page: https://github.com/hexadecimalDinosaur/octoprint-cli
Author: Ivy Fan-Chiang
Author-email: dev@ivyfanchiang.ca
Classifier: Programming Language :: Python :: 3
Classifier: License :: OSI Approved :: GNU General Public License v3 (GPLv3)
Classifier: Operating System :: OS Independent
Classifier: Natural Language :: English
Classifier: Environment :: Console
Requires-Python: >=3.6
License-File: LICENSE
Requires-Dist: requests>=2.23.0
Requires-Dist: termcolor>=1.1.0
Dynamic: author
Dynamic: author-email
Dynamic: classifier
Dynamic: description
Dynamic: description-content-type
Dynamic: home-page
Dynamic: license-file
Dynamic: requires-dist
Dynamic: requires-python
Dynamic: summary
